cwltest/__init__.py
cwltest/__main__.py
cwltest/_version.py
cwltest/argparser.py
cwltest/compare.py
cwltest/cwltest-schema-strict.yml
cwltest/cwltest-schema.yml
cwltest/hooks.py
cwltest/main.py
cwltest/plugin.py
cwltest/py.typed
cwltest/stdfsaccess.py
cwltest/utils.py
cwltest/tests/__init__.py
cwltest/tests/test_argparse.py
cwltest/tests/test_badgedir.py
cwltest/tests/test_categories.py
cwltest/tests/test_compare.py
cwltest/tests/test_exclude_tags.py
cwltest/tests/test_integer_id.py
cwltest/tests/test_invalid_outputs.py
cwltest/tests/test_multi_lined_doc.py
cwltest/tests/test_numeric_id.py
cwltest/tests/test_plugin.py
cwltest/tests/test_prepare.py
cwltest/tests/test_short_names.py
cwltest/tests/test_string_id.py
cwltest/tests/test_timeout.py
cwltest/tests/util.py
cwltest/tests/test-data/badgedir.yaml
cwltest/tests/test-data/conformance_test_v1.0.cwltest.yml
cwltest/tests/test-data/conformance_test_v1.2.cwltest.yaml
cwltest/tests/test-data/cores.txt
cwltest/tests/test-data/cwltool-conftest.py
cwltest/tests/test-data/dummy-executor.sh
cwltest/tests/test-data/empty.yml
cwltest/tests/test-data/exclude-tags.yml
cwltest/tests/test-data/integer-id.yml
cwltest/tests/test-data/mock_cwl_runner.py
cwltest/tests/test-data/multi-lined-doc.yml
cwltest/tests/test-data/nothing.yml
cwltest/tests/test-data/optional-error.yml
cwltest/tests/test-data/optional-unsupported.yml
cwltest/tests/test-data/required-unsupported.yml
cwltest/tests/test-data/return-0.cwl
cwltest/tests/test-data/return-1.cwl
cwltest/tests/test-data/return-unsupported.cwl
cwltest/tests/test-data/short-names.yml
cwltest/tests/test-data/string-id.yml
cwltest/tests/test-data/timeout.cwl
cwltest/tests/test-data/timeout.yml
cwltest/tests/test-data/true.cwl
cwltest/tests/test-data/with-and-without-short-names.yml
cwltest/tests/test-data/v1.0/args.py
cwltest/tests/test-data/v1.0/cat-job.json
cwltest/tests/test-data/v1.0/cat-n-job.json
cwltest/tests/test-data/v1.0/cat1-job.json
cwltest/tests/test-data/v1.0/cat1-testcli.cwl
cwltest-2.6.20251216093331.dist-info/licenses/LICENSE
cwltest-2.6.20251216093331.dist-info/METADATA
cwltest-2.6.20251216093331.dist-info/WHEEL
cwltest-2.6.20251216093331.dist-info/entry_points.txt
cwltest-2.6.20251216093331.dist-info/top_level.txt
cwltest-2.6.20251216093331.dist-info/zip-safe
cwltest-2.6.20251216093331.dist-info/RECORD
